boum/api_client/constants.py
boum/api_client/v1/client.py
boum/api_client/v1/endpoint.py
boum/api_client/v1/models.py
boum/resources/device.py
boum-1.4.0.dist-info/LICENSE
boum-1.4.0.dist-info/WHEEL
boum-1.4.0.dist-info/METADATA
boum-1.4.0.dist-info/RECORD
