Metadata-Version: 2.1
Name: boum
Version: 1.4.0
Summary: SDK to interact with the boum API
Home-page: https://github.com/boum-garden/sdk
License: MIT
Author: Marc Pfander
Author-email: marc.pfander@boum.garden
Requires-Python: >=3.10,<4.0
Classifier: License :: OSI Approved :: MIT License
Classifier: Programming Language :: Python :: 3
Classifier: Programming Language :: Python :: 3.10
Classifier: Programming Language :: Python :: 3.11
Requires-Dist: requests (>=2.28.1,<3.0.0)
Project-URL: Repository, https://github.com/boum-garden/sdk
